sorna_jupyter_kernel-0.1.3-py3.6-nspkg.pth
sorna/integration/jupyter/__init__.py
sorna/integration/jupyter/__main__.py
sorna/integration/jupyter/install.py
sorna/integration/jupyter/kernel.py
sorna_jupyter_kernel-0.1.3.dist-info/DESCRIPTION.rst
sorna_jupyter_kernel-0.1.3.dist-info/METADATA
sorna_jupyter_kernel-0.1.3.dist-info/RECORD
sorna_jupyter_kernel-0.1.3.dist-info/WHEEL
sorna_jupyter_kernel-0.1.3.dist-info/metadata.json
sorna_jupyter_kernel-0.1.3.dist-info/namespace_packages.txt
sorna_jupyter_kernel-0.1.3.dist-info/top_level.txt
